buildlink/__init__.py
buildlink/buildlink.py
buildlink-1.0.0.dist-info/LICENSE
buildlink-1.0.0.dist-info/METADATA
buildlink-1.0.0.dist-info/WHEEL
buildlink-1.0.0.dist-info/entry_points.txt
buildlink-1.0.0.dist-info/top_level.txt
buildlink-1.0.0.dist-info/RECORD
