Metadata-Version: 2.1
Name: buildlink
Version: 1.0.0
Summary: buildlink is a python program which helps you to shorten link with a single command without any registration or using any API Key.Its also provide option to expand any link available on internet on wide range of domain names.
Home-page: https://github.com/TechUX/buildlink
Author: Devesh Singh
Author-email: connect.world12345@gmail.com
License: MIT
Keywords: link
Platform: UNKNOWN
Classifier: License :: OSI Approved :: MIT License
Classifier: Operating System :: OS Independent
Classifier: Programming Language :: Python
Requires-Python: >=2.0
License-File: LICENSE
